cloudtower/__init__.py
cloudtower/api_client.py
cloudtower/configuration.py
cloudtower/exceptions.py
cloudtower/image_utils.py
cloudtower/rest.py
cloudtower/utils.py
cloudtower/api/__init__.py
cloudtower/api/alert_api.py
cloudtower/api/alert_notifier_api.py
cloudtower/api/alert_rule_api.py
cloudtower/api/api_info_api.py
cloudtower/api/application_api.py
cloudtower/api/brick_topo_api.py
cloudtower/api/cloud_tower_application_api.py
cloudtower/api/cloud_tower_application_package_api.py
cloudtower/api/cluster_api.py
cloudtower/api/cluster_image_api.py
cloudtower/api/cluster_settings_api.py
cloudtower/api/cluster_topo_api.py
cloudtower/api/cluster_upgrade_history_api.py
cloudtower/api/consistency_group_api.py
cloudtower/api/consistency_group_snapshot_api.py
cloudtower/api/content_library_image_api.py
cloudtower/api/content_library_vm_template_api.py
cloudtower/api/datacenter_api.py
cloudtower/api/deploy_api.py
cloudtower/api/discovered_host_api.py
cloudtower/api/disk_api.py
cloudtower/api/elf_data_store_api.py
cloudtower/api/elf_image_api.py
cloudtower/api/elf_storage_policy_api.py
cloudtower/api/entity_filter_api.py
cloudtower/api/everoute_cluster_api.py
cloudtower/api/everoute_license_api.py
cloudtower/api/everoute_package_api.py
cloudtower/api/global_alert_rule_api.py
cloudtower/api/global_settings_api.py
cloudtower/api/gpu_device_api.py
cloudtower/api/graph_api.py
cloudtower/api/host_api.py
cloudtower/api/ipmi_api.py
cloudtower/api/iscsi_connection_api.py
cloudtower/api/iscsi_lun_api.py
cloudtower/api/iscsi_lun_snapshot_api.py
cloudtower/api/iscsi_target_api.py
cloudtower/api/isolation_policy_api.py
cloudtower/api/label_api.py
cloudtower/api/license_api.py
cloudtower/api/log_collection_api.py
cloudtower/api/log_service_config_api.py
cloudtower/api/metrics_api.py
cloudtower/api/namespace_group_api.py
cloudtower/api/nfs_export_api.py
cloudtower/api/nfs_inode_api.py
cloudtower/api/nic_api.py
cloudtower/api/node_topo_api.py
cloudtower/api/nvmf_namespace_api.py
cloudtower_sdk-2.17.0.dist-info/LICENSE
cloudtower_sdk-2.17.0.dist-info/METADATA
cloudtower_sdk-2.17.0.dist-info/WHEEL
cloudtower_sdk-2.17.0.dist-info/top_level.txt
cloudtower_sdk-2.17.0.dist-info/RECORD
