Metadata-Version: 2.1
Name: cloudtower-sdk
Version: 2.17.0
Summary: CloudTower APIs
Home-page: https://github.com/smartxworks/cloudtower-python-sdk
Author: Cloudtower developers
Author-email: info@smartx.com
License: UNKNOWN
Keywords: OpenAPI,OpenAPI-Generator,CloudTower APIs
Platform: UNKNOWN
Requires-Dist: urllib3 (>=1.25.3)
Requires-Dist: six (>=1.10)
Requires-Dist: python-dateutil
